cache/__init__.py
cache/data_sources/__init__.py
cache/data_sources/repository/__init__.py
cache/data_sources/repository/cache_service_impl.py
cache/decorators/__init__.py
cache/decorators/cache_result.py
cache/domain/__init__.py
cache/domain/factories/__init__.py
cache/domain/factories/cache_service_factory.py
cache/domain/repository/__init__.py
cache/domain/repository/cache_service.py
python_cache_service-0.1.1.dist-info/licenses/LICENCE
python_cache_service-0.1.1.dist-info/METADATA
python_cache_service-0.1.1.dist-info/WHEEL
python_cache_service-0.1.1.dist-info/top_level.txt
python_cache_service-0.1.1.dist-info/RECORD
