Metadata-Version: 2.4
Name: python-cache-service
Version: 0.1.1
Summary: Simple namespaced cache service using Redis
Home-page: https://gitlab.com/Johannesbrochdue/python-cache-service
Author: Johannes Broch-Due
Author-email: Johannes Broch-Due <johannesbrochdue@gmail.com>
Project-URL: Homepage, https://gitlab.com/Johannesbrochdue/python-cache-service
Project-URL: Repository, https://gitlab.com/Johannesbrochdue/python-cache-service
Requires-Python: >=3.8
License-File: LICENCE
Requires-Dist: redis
Requires-Dist: fakeredis
Dynamic: author
Dynamic: home-page
Dynamic: license-file
Dynamic: requires-python
